main.py
gemini_cli_mcp-0.1.5.dist-info/METADATA
gemini_cli_mcp-0.1.5.dist-info/WHEEL
gemini_cli_mcp-0.1.5.dist-info/entry_points.txt
gemini_cli_mcp-0.1.5.dist-info/top_level.txt
gemini_cli_mcp-0.1.5.dist-info/RECORD
