Metadata-Version: 2.4
Name: gemini-cli-mcp
Version: 0.1.5
Summary: Gemini CLI MCP Server
Requires-Python: >=3.12
Requires-Dist: fastapi>=0.116.0
Requires-Dist: mcp[cli]>=1.10.1
Requires-Dist: pytest>=8.4.1
Requires-Dist: python-dotenv>=1.1.1
Requires-Dist: uv>=0.7.20
Requires-Dist: uvicorn>=0.35.0
